galitime/__init__.py
galitime/galitime.py
galitime/increment_version.py
galitime/version.py
galitime-0.2.0.dist-info/LICENSE.txt
galitime-0.2.0.dist-info/METADATA
galitime-0.2.0.dist-info/WHEEL
galitime-0.2.0.dist-info/entry_points.txt
galitime-0.2.0.dist-info/top_level.txt
galitime-0.2.0.dist-info/RECORD
